rokso/__init__.py
rokso/rokso.py
rokso/lib/__init__.py
rokso/lib/agent.py
rokso/lib/configManager.py
rokso/lib/connectionManager.py
rokso/lib/dbManager.py
rokso/lib/migrationManager.py
rokso-0.1.15.dist-info/LICENSE.md
rokso-0.1.15.dist-info/METADATA
rokso-0.1.15.dist-info/WHEEL
rokso-0.1.15.dist-info/entry_points.txt
rokso-0.1.15.dist-info/top_level.txt
rokso-0.1.15.dist-info/RECORD
